s3streamer/__init__.py
s3streamer/s3streamer.py
s3streamer-2024.1.0.0.dist-info/METADATA
s3streamer-2024.1.0.0.dist-info/WHEEL
s3streamer-2024.1.0.0.dist-info/RECORD
